devscasino/__init__.py
devscasino/game.py
devscasino-0.1.1.dist-info/licenses/LICENSE
devscasino-0.1.1.dist-info/METADATA
devscasino-0.1.1.dist-info/WHEEL
devscasino-0.1.1.dist-info/top_level.txt
devscasino-0.1.1.dist-info/RECORD
